keylex/__init__.py
keylex/matchers/__init__.py
keylex/matchers/enums.py
keylex/matchers/keyword.py
keylex/matchers/keyword_list.py
keylex/matchers/matcher.py
keylex-0.0.2.dist-info/METADATA
keylex-0.0.2.dist-info/WHEEL
keylex-0.0.2.dist-info/licenses/LICENSE
keylex-0.0.2.dist-info/RECORD
