Metadata-Version: 2.4
Name: keylex
Version: 0.0.2
Summary: A modular library for keyword matching and extraction.
Author-email: Konstantinos Giannopoulos <giannopoulosk.data@gmail.com>
License: Apache License 2.0
License-File: LICENSE
Requires-Python: <3.13,>=3.11
Requires-Dist: rapidfuzz==3.13.0
Provides-Extra: dev
Requires-Dist: mypy<0.920,>=0.910; extra == 'dev'
Requires-Dist: pytest<7.0.0,>=6.2.5; extra == 'dev'
Requires-Dist: ruff<0.12.0,>=0.11.4; extra == 'dev'
